[
    {
        "title": "تلویزیون سونی مدل XR50 سایز ۹۸ اینچ LED Ultra HD 4K",
        "brand": "سونی",
        "size": "۹۸ اینچ",
        "tech": "LED",
        "num_sellers": "۱۴",
        "avg_price_top5": "980 تومان",
        "link": "https://torob.com/browse/246/تلویزیون-tv/b/4616/gplus-%D8%AC%DB%8C-%D9%BE%D9%84%D8%A7%D8%B3/"
    },
    {
        "title": "تلویزیون سونی مدل XR50 سایز ۹۸ اینچ LED Ultra HD 4K",
        "brand": "سونی",
        "size": "۹۸ اینچ",
        "tech": "LED",
        "num_sellers": "۱۴",
        "avg_price_top5": "980 تومان",
        "link": "https://torob.com/"
    },
    {
        "title": "تلویزیون سونی مدل XR50 سایز ۹۸ اینچ LED Ultra HD 4K",
        "brand": "سونی",
        "size": "۹۸ اینچ",
        "tech": "LED",
        "num_sellers": "۱۴",
        "avg_price_top5": "980 تومان",
        "link": "https://torob.com/p/97f1e08f-2106-448f-97cb-4166a96f4dd4/%D8%AA%D9%84%D9%88%DB%8C%D8%B2%DB%8C%D9%88%D9%86-%D8%B3%D9%88%D9%86%DB%8C-%D9%85%D8%AF%D9%84-xr50-%D8%B3%D8%A7%DB%8C%D8%B2-98-%D8%A7%DB%8C%D9%86%DA%86-led-ultra-hd-4k/"
    },
    {
        "title": "تلویزیون سونی مدل XR50 سایز ۹۸ اینچ LED Ultra HD 4K",
        "brand": "سونی",
        "size": "۹۸ اینچ",
        "tech": "LED",
        "num_sellers": "۱۴",
        "avg_price_top5": "980 تومان",
        "link": "https://torob.com/p/97f1e08f-2106-448f-97cb-4166a96f4dd4/%D8%AA%D9%84%D9%88%DB%8C%D8%B2%DB%8C%D9%88%D9%86-%D8%B3%D9%88%D9%86%DB%8C-%D9%85%D8%AF%D9%84-xr50-%D8%B3%D8%A7%DB%8C%D8%B2-98-%D8%A7%DB%8C%D9%86%DA%86-led-ultra-hd-4k/"
    },
    {
        "title": "تلویزیون سونی مدل XR50 سایز ۹۸ اینچ LED Ultra HD 4K",
        "brand": "سونی",
        "size": "۹۸ اینچ",
        "tech": "LED",
        "num_sellers": "نامشخص",
        "avg_price_top5": "980 تومان",
        "link": ""
    },
    {
        "title": "تلویزیون سامسونگ QN900D سایز ۸۵ اینچ QLED",
        "brand": "سامسونگ",
        "size": "۸۵ اینچ",
        "tech": "QLED",
        "num_sellers": "نامشخص",
        "avg_price_top5": "900 تومان",
        "link": ""
    },
    {
        "title": "تلویزیون سامسونگ QN900C سایز ۸۵ اینچ Ultra HD 4K QLED",
        "brand": "سامسونگ",
        "size": "۸۵ اینچ",
        "tech": "4K",
        "num_sellers": "نامشخص",
        "avg_price_top5": "800 تومان",
        "link": ""
    },
    {
        "title": "تلویزیون هوشمند بلانتون مدل BEW-TV6523 سایز 65 اینچ 4K",
        "brand": "نامشخص",
        "size": "65 اینچ",
        "tech": "4K",
        "num_sellers": "نامشخص",
        "avg_price_top5": "766 تومان",
        "link": ""
    },
    {
        "title": "تلویزیون سونی مدل XR90 سایز ۸۵ اینچ Ultra HD 4K LED",
        "brand": "سونی",
        "size": "۸۵ اینچ",
        "tech": "4K",
        "num_sellers": "۱۴",
        "avg_price_top5": "740 تومان",
        "link": ""
    },
    {
        "title": "تلویزیون سونی مدل X90L سایز ۹۸ اینچ LED Ultra HD 4K",
        "brand": "سونی",
        "size": "۹۸ اینچ",
        "tech": "LED",
        "num_sellers": "۵",
        "avg_price_top5": "719 تومان",
        "link": ""
    },
    {
        "title": "تلویزیون سامسونگ QN900D سایز ۷۵ اینچ کیفیت Ultra HD 4K نوع QLED",
        "brand": "سامسونگ",
        "size": "۷۵ اینچ",
        "tech": "4K",
        "num_sellers": "نامشخص",
        "avg_price_top5": "700 تومان",
        "link": ""
    },
    {
        "title": "تلویزیون سونی مدل XR80M2 سایز ۶۵ اینچ OLED Ultra HD 4K",
        "brand": "سونی",
        "size": "۶۵ اینچ",
        "tech": "OLED",
        "num_sellers": "نامشخص",
        "avg_price_top5": "650 تومان",
        "link": ""
    },
    {
        "title": "تلویزیون سونی X95L سایز ۷۵ اینچ Ultra HD 4K LED",
        "brand": "سونی",
        "size": "۷۵ اینچ",
        "tech": "4K",
        "num_sellers": "نامشخص",
        "avg_price_top5": "640 تومان",
        "link": ""
    },
    {
        "title": "تلویزیون ال جی G4 سایز ۸۳ اینچ OLED Ultra HD 4K",
        "brand": "ال جی",
        "size": "۸۳ اینچ",
        "tech": "OLED",
        "num_sellers": "۷",
        "avg_price_top5": "639 تومان",
        "link": ""
    },
    {
        "title": "تلویزیون سامسونگ مدل QN90D سایز ۸۵ اینچ Ultra HD 4K QLED",
        "brand": "سامسونگ",
        "size": "۸۵ اینچ",
        "tech": "4K",
        "num_sellers": "نامشخص",
        "avg_price_top5": "590 تومان",
        "link": ""
    },
    {
        "title": "تلویزیون سامسونگ QN80F کیفیت تصویر Ultra HD 4K",
        "brand": "سامسونگ",
        "size": "نامشخص",
        "tech": "4K",
        "num_sellers": "۲",
        "avg_price_top5": "581 تومان",
        "link": ""
    },
    {
        "title": "تلویزیون سامسونگ مدل QN80F سایز ۱۰۰ اینچ Ultra HD 4K QLED",
        "brand": "سامسونگ",
        "size": "۱۰۰ اینچ",
        "tech": "4K",
        "num_sellers": "۴",
        "avg_price_top5": "581 تومان",
        "link": ""
    },
    {
        "title": "تلویزیون سامسونگ Q80C سایز ۹۸ اینچ کیفیت Ultra HD 4K QLED",
        "brand": "سامسونگ",
        "size": "۹۸ اینچ",
        "tech": "4K",
        "num_sellers": "۳",
        "avg_price_top5": "577 تومان",
        "link": ""
    },
    {
        "title": "تلویزیون هوشمند بلانتون ۵۸ اینچ مدل BEF-TV5840",
        "brand": "نامشخص",
        "size": "۵۸ اینچ",
        "tech": "نامشخص",
        "num_sellers": "نامشخص",
        "avg_price_top5": "576 تومان",
        "link": ""
    },
    {
        "title": "تلویزیون سونی مدل 85RX90 سایز ۸۵ اینچ",
        "brand": "سونی",
        "size": "۸۵ اینچ",
        "tech": "نامشخص",
        "num_sellers": "نامشخص",
        "avg_price_top5": "543 تومان",
        "link": ""
    },
    {
        "title": "تلویزیون فیلیپس مدل 77OLED818 سایز ۷۷ اینچ OLED Ultra HD 4K",
        "brand": "نامشخص",
        "size": "۷۷ اینچ",
        "tech": "OLED",
        "num_sellers": "نامشخص",
        "avg_price_top5": "528 تومان",
        "link": ""
    },
    {
        "title": "تلویزیون سامسونگ QN800D سایز ۸۵ اینچ QLED Ultra HD 4K",
        "brand": "سامسونگ",
        "size": "۸۵ اینچ",
        "tech": "QLED",
        "num_sellers": "۳",
        "avg_price_top5": "525 تومان",
        "link": ""
    },
    {
        "title": "تلویزیون سونی مدل A80L سایز ۸۳ اینچ اولد Ultra HD 4K",
        "brand": "سونی",
        "size": "۸۳ اینچ",
        "tech": "4K",
        "num_sellers": "نامشخص",
        "avg_price_top5": "500 تومان",
        "link": ""
    },
    {
        "title": "تلویزیون سونی مدل XR80 سایز ۷۵ اینچ",
        "brand": "سونی",
        "size": "۷۵ اینچ",
        "tech": "نامشخص",
        "num_sellers": "۲",
        "avg_price_top5": "489 تومان",
        "link": ""
    },
    {
        "title": "تلویزیون ال جی مدل QNED86 سایز ۱۰۰ اینچ Ultra HD 4K",
        "brand": "ال جی",
        "size": "۱۰۰ اینچ",
        "tech": "4K",
        "num_sellers": "۸",
        "avg_price_top5": "468 تومان",
        "link": ""
    },
    {
        "title": "تلویزیون سونی XR80 سایز ۷۷ اینچ OLED کیفیت تصویر Ultra HD 4K",
        "brand": "سونی",
        "size": "۷۷ اینچ",
        "tech": "OLED",
        "num_sellers": "۵",
        "avg_price_top5": "460 تومان",
        "link": ""
    },
    {
        "title": "تلویزیون سونی ۹۸ اینچ مدل 98bzl50",
        "brand": "سونی",
        "size": "۹۸ اینچ",
        "tech": "نامشخص",
        "num_sellers": "نامشخص",
        "avg_price_top5": "430 تومان",
        "link": ""
    },
    {
        "title": "تلویزیون سونی BZ50L سایز ۹۸ اینچ Ultra HD 4K LED",
        "brand": "سونی",
        "size": "۹۸ اینچ",
        "tech": "4K",
        "num_sellers": "۸",
        "avg_price_top5": "430 تومان",
        "link": ""
    },
    {
        "title": "تلویزیون سونی مدل X95L سایز ۸۵ اینچ Ultra HD 4K LED",
        "brand": "سونی",
        "size": "۸۵ اینچ",
        "tech": "4K",
        "num_sellers": "۶",
        "avg_price_top5": "430 تومان",
        "link": ""
    },
    {
        "title": "تلویزیون سونی مدل XR50 سایز ۸۵ اینچ LED Ultra HD 4K",
        "brand": "سونی",
        "size": "۸۵ اینچ",
        "tech": "LED",
        "num_sellers": "۱۲",
        "avg_price_top5": "430 تومان",
        "link": ""
    },
    {
        "title": "تلویزیون سونی مدل 98BZL50 سایز ۹۸ اینچ",
        "brand": "سونی",
        "size": "۹۸ اینچ",
        "tech": "نامشخص",
        "num_sellers": "۲",
        "avg_price_top5": "430 تومان",
        "link": ""
    },
    {
        "title": "تلویزیون ال ای دی سونی مدل براویا ۹ XR90 سایز ۷۵ اینچ",
        "brand": "سونی",
        "size": "۷۵ اینچ",
        "tech": "نامشخص",
        "num_sellers": "۱۳",
        "avg_price_top5": "429 تومان",
        "link": ""
    },
    {
        "title": "تلویزیون هایسنس UX سایز ۸۵ اینچ Ultra HD 4K LED",
        "brand": "هایسنس",
        "size": "۸۵ اینچ",
        "tech": "4K",
        "num_sellers": "۲",
        "avg_price_top5": "428 تومان",
        "link": "https://torob.com/browse/246/تلویزیون-tv/b/4616/gplus-%D8%AC%DB%8C-%D9%BE%D9%84%D8%A7%D8%B3/"
    },
    {
        "title": "تلویزیون هایسنس UX سایز ۸۵ اینچ Ultra HD 4K LED",
        "brand": "هایسنس",
        "size": "۸۵ اینچ",
        "tech": "4K",
        "num_sellers": "۲",
        "avg_price_top5": "428 تومان",
        "link": "https://torob.com/"
    },
    {
        "title": "تلویزیون هایسنس UX سایز ۸۵ اینچ Ultra HD 4K LED",
        "brand": "هایسنس",
        "size": "۸۵ اینچ",
        "tech": "4K",
        "num_sellers": "۲",
        "avg_price_top5": "428 تومان",
        "link": "https://torob.com/p/199f38f8-2152-4837-a484-4814764912e5/%D8%AA%D9%84%D9%88%DB%8C%D8%B2%DB%8C%D9%88%D9%86-%D9%87%D8%A7%DB%8C%D8%B3%D9%86%D8%B3-ux-%D8%B3%D8%A7%DB%8C%D8%B2-85-%D8%A7%DB%8C%D9%86%DA%86-ultra-hd-4k-led/"
    },
    {
        "title": "تلویزیون هایسنس UX سایز ۸۵ اینچ Ultra HD 4K LED",
        "brand": "هایسنس",
        "size": "۸۵ اینچ",
        "tech": "4K",
        "num_sellers": "۲",
        "avg_price_top5": "428 تومان",
        "link": "https://torob.com/p/199f38f8-2152-4837-a484-4814764912e5/%D8%AA%D9%84%D9%88%DB%8C%D8%B2%DB%8C%D9%88%D9%86-%D9%87%D8%A7%DB%8C%D8%B3%D9%86%D8%B3-ux-%D8%B3%D8%A7%DB%8C%D8%B2-85-%D8%A7%DB%8C%D9%86%DA%86-ultra-hd-4k-led/"
    },
    {
        "title": "تلویزیون هایسنس UX سایز ۸۵ اینچ Ultra HD 4K LED",
        "brand": "هایسنس",
        "size": "۸۵ اینچ",
        "tech": "4K",
        "num_sellers": "۲",
        "avg_price_top5": "428 تومان",
        "link": ""
    },
    {
        "title": "تلویزیون سامسونگ مدل QN90D سایز ۷۵ اینچ Ultra HD 4K QLED",
        "brand": "سامسونگ",
        "size": "۷۵ اینچ",
        "tech": "4K",
        "num_sellers": "نامشخص",
        "avg_price_top5": "420 تومان",
        "link": ""
    },
    {
        "title": "تلویزیون سامسونگ S90D سایز ۸۳ اینچ OLED Ultra HD 4K",
        "brand": "سامسونگ",
        "size": "۸۳ اینچ",
        "tech": "OLED",
        "num_sellers": "۸",
        "avg_price_top5": "412 تومان",
        "link": ""
    },
    {
        "title": "تلویزیون سامسونگ QN800D سایز ۷۵ اینچ QLED Ultra HD 4K",
        "brand": "سامسونگ",
        "size": "۷۵ اینچ",
        "tech": "QLED",
        "num_sellers": "نامشخص",
        "avg_price_top5": "410 تومان",
        "link": ""
    },
    {
        "title": "تلویزیون هوشمند ال جی OLED77C56 سایز ۷۷ اینچ Ultra HD 4K",
        "brand": "ال جی",
        "size": "۷۷ اینچ",
        "tech": "OLED",
        "num_sellers": "نامشخص",
        "avg_price_top5": "405 تومان",
        "link": ""
    },
    {
        "title": "تلویزیون ال جی QNED89 سایز ۹۸ اینچ Ultra HD 4K",
        "brand": "ال جی",
        "size": "۹۸ اینچ",
        "tech": "4K",
        "num_sellers": "۹",
        "avg_price_top5": "402 تومان",
        "link": ""
    },
    {
        "title": "تلویزیون ال جی C3 سایز ۸۳ اینچ اولد Ultra HD 4K",
        "brand": "ال جی",
        "size": "۸۳ اینچ",
        "tech": "4K",
        "num_sellers": "۶",
        "avg_price_top5": "400 تومان",
        "link": ""
    },
    {
        "title": "تلویزیون سامسونگ مدل LS03 سایز ۸۵ اینچ Ultra HD 4K",
        "brand": "سامسونگ",
        "size": "۸۵ اینچ",
        "tech": "4K",
        "num_sellers": "نامشخص",
        "avg_price_top5": "400 تومان",
        "link": ""
    },
    {
        "title": "تلویزیون سامسونگ QN900D سایز ۶۵ اینچ کیفیت Ultra HD 4K نوع QLED",
        "brand": "سامسونگ",
        "size": "۶۵ اینچ",
        "tech": "4K",
        "num_sellers": "نامشخص",
        "avg_price_top5": "400 تومان",
        "link": ""
    },
    {
        "title": "تلویزیون سونی مدل XR70 سایز ۸۵ اینچ کیفیت تصویر Ultra HD 4K نوع نمایش QLED",
        "brand": "سونی",
        "size": "۸۵ اینچ",
        "tech": "4K",
        "num_sellers": "۱۴",
        "avg_price_top5": "399 تومان",
        "link": ""
    },
    {
        "title": "تلویزیون سامسونگ مدل QN900C سایز ۷۵ اینچ Ultra HD 4K QLED",
        "brand": "سامسونگ",
        "size": "۷۵ اینچ",
        "tech": "4K",
        "num_sellers": "۲",
        "avg_price_top5": "399 تومان",
        "link": ""
    },
    {
        "title": "تلویزیون ال جی QNED99 سایز ۸۶ اینچ Ultra HD 4K",
        "brand": "ال جی",
        "size": "۸۶ اینچ",
        "tech": "4K",
        "num_sellers": "۲",
        "avg_price_top5": "397 تومان",
        "link": ""
    },
    {
        "title": "تلویزیون ال جی مدل G5 سایز ۷۷ اینچ OLED Ultra HD 4K",
        "brand": "ال جی",
        "size": "۷۷ اینچ",
        "tech": "OLED",
        "num_sellers": "۲",
        "avg_price_top5": "389 تومان",
        "link": ""
    },
    {
        "title": "تلویزیون سونی مدل RX70 سایز ۸۵ اینچ",
        "brand": "سونی",
        "size": "۸۵ اینچ",
        "tech": "نامشخص",
        "num_sellers": "نامشخص",
        "avg_price_top5": "375 تومان",
        "link": ""
    },
    {
        "title": "تلویزیون ال جی G4 سایز ۷۷ اینچ اولد Ultra HD 4K",
        "brand": "ال جی",
        "size": "۷۷ اینچ",
        "tech": "4K",
        "num_sellers": "۵",
        "avg_price_top5": "374 تومان",
        "link": ""
    },
    {
        "title": "تلویزیون سامسونگ S90D سایز ۷۷ اینچ OLED Ultra HD 4K",
        "brand": "سامسونگ",
        "size": "۷۷ اینچ",
        "tech": "OLED",
        "num_sellers": "۳",
        "avg_price_top5": "374 تومان",
        "link": ""
    },
    {
        "title": "تلویزیون سونی A80L سایز ۶۵ اینچ OLED کیفیت تصویر Ultra HD 4K",
        "brand": "سونی",
        "size": "۶۵ اینچ",
        "tech": "OLED",
        "num_sellers": "نامشخص",
        "avg_price_top5": "373 تومان",
        "link": ""
    },
    {
        "title": "تلویزیون هایسنس مدل Q7Q سایز ۱۰۰ اینچ Ultra HD 4K",
        "brand": "هایسنس",
        "size": "۱۰۰ اینچ",
        "tech": "4K",
        "num_sellers": "نامشخص",
        "avg_price_top5": "360 تومان",
        "link": ""
    },
    {
        "title": "تلویزیون سامسونگ QN800C سایز ۷۵ اینچ QLED Ultra HD 4K",
        "brand": "سامسونگ",
        "size": "۷۵ اینچ",
        "tech": "QLED",
        "num_sellers": "نامشخص",
        "avg_price_top5": "360 تومان",
        "link": ""
    },
    {
        "title": "تلویزیون ال جی مدل C5 سایز ۷۷ اینچ OLED Ultra HD 4K",
        "brand": "ال جی",
        "size": "۷۷ اینچ",
        "tech": "OLED",
        "num_sellers": "۸",
        "avg_price_top5": "358 تومان",
        "link": ""
    },
    {
        "title": "تلویزیون 98 اینچ کیو ال ای دی هوشمند جی پلاس مدل GTV-98SQ878SP",
        "brand": "جی پلاس",
        "size": "98 اینچ",
        "tech": "نامشخص",
        "num_sellers": "نامشخص",
        "avg_price_top5": "357 تومان",
        "link": ""
    },
    {
        "title": "تلویزیون هوشمند ایکس ویژن مدل X15 سایز ۱۰۰ اینچ QLED Ultra HD 4K",
        "brand": "ایکس ویژن",
        "size": "۱۰۰ اینچ",
        "tech": "QLED",
        "num_sellers": "۲",
        "avg_price_top5": "350 تومان",
        "link": ""
    },
    {
        "title": "تلویزیون سامسونگ مدل QN900C سایز ۶۵ اینچ QLED Ultra HD 4K",
        "brand": "سامسونگ",
        "size": "۶۵ اینچ",
        "tech": "QLED",
        "num_sellers": "نامشخص",
        "avg_price_top5": "350 تومان",
        "link": ""
    },
    {
        "title": "تلویزیون تی سی ال مدل C755 سایز ۹۸ اینچ کیفیت Ultra HD 4K LED",
        "brand": "تی سی ال",
        "size": "۹۸ اینچ",
        "tech": "4K",
        "num_sellers": "۳",
        "avg_price_top5": "350 تومان",
        "link": ""
    },
    {
        "title": "تلویزیون ال جی C5",
        "brand": "ال جی",
        "size": "نامشخص",
        "tech": "نامشخص",
        "num_sellers": "نامشخص",
        "avg_price_top5": "349 تومان",
        "link": ""
    },
    {
        "title": "تلویزیون سونی X90L سایز ۸۵ اینچ کیفیت ۴K LED",
        "brand": "سونی",
        "size": "۸۵ اینچ",
        "tech": "LED",
        "num_sellers": "۱۹",
        "avg_price_top5": "348 تومان",
        "link": ""
    },
    {
        "title": "تلویزیون ال جی 85 اینچ مدل 85QNED93A 2025",
        "brand": "ال جی",
        "size": "85 اینچ",
        "tech": "نامشخص",
        "num_sellers": "نامشخص",
        "avg_price_top5": "340 تومان",
        "link": ""
    },
    {
        "title": "تلویزیون سونی مدل XR70 سایز ۷۵ اینچ کیفیت تصویر Ultra HD 4K نوع نمایش QLED",
        "brand": "سونی",
        "size": "۷۵ اینچ",
        "tech": "4K",
        "num_sellers": "۱۸",
        "avg_price_top5": "339 تومان",
        "link": ""
    },
    {
        "title": "تلویزیون سامسونگ QA85QN85fan",
        "brand": "سامسونگ",
        "size": "نامشخص",
        "tech": "نامشخص",
        "num_sellers": "نامشخص",
        "avg_price_top5": "335 تومان",
        "link": ""
    },
    {
        "title": "تلویزیون سامسونگ QN90D",
        "brand": "سامسونگ",
        "size": "نامشخص",
        "tech": "نامشخص",
        "num_sellers": "نامشخص",
        "avg_price_top5": "334 تومان",
        "link": ""
    },
    {
        "title": "تلویزیون جی پلاس مدل GTV-98SQ866S سایز ۹۸ اینچ QLED Ultra HD 4K",
        "brand": "جی پلاس",
        "size": "۹۸ اینچ",
        "tech": "QLED",
        "num_sellers": "۲",
        "avg_price_top5": "332 تومان",
        "link": "https://torob.com/browse/246/تلویزیون-tv/b/4616/gplus-%D8%AC%DB%8C-%D9%BE%D9%84%D8%A7%D8%B3/"
    },
    {
        "title": "تلویزیون جی پلاس مدل GTV-98SQ866S سایز ۹۸ اینچ QLED Ultra HD 4K",
        "brand": "جی پلاس",
        "size": "۹۸ اینچ",
        "tech": "QLED",
        "num_sellers": "۲",
        "avg_price_top5": "332 تومان",
        "link": "https://torob.com/"
    },
    {
        "title": "تلویزیون جی پلاس مدل GTV-98SQ866S سایز ۹۸ اینچ QLED Ultra HD 4K",
        "brand": "جی پلاس",
        "size": "۹۸ اینچ",
        "tech": "QLED",
        "num_sellers": "۲",
        "avg_price_top5": "332 تومان",
        "link": "https://torob.com/p/51267344-c620-4d05-9834-2cbad796a683/%D8%AA%D9%84%D9%88%DB%8C%D8%B2%DB%8C%D9%88%D9%86-%D8%AC%DB%8C-%D9%BE%D9%84%D8%A7%D8%B3-%D9%85%D8%AF%D9%84-gtv-98sq866s-%D8%B3%D8%A7%DB%8C%D8%B2-98-%D8%A7%DB%8C%D9%86%DA%86-qled-ultra-hd-4k/"
    },
    {
        "title": "تلویزیون جی پلاس مدل GTV-98SQ866S سایز ۹۸ اینچ QLED Ultra HD 4K",
        "brand": "جی پلاس",
        "size": "۹۸ اینچ",
        "tech": "QLED",
        "num_sellers": "۲",
        "avg_price_top5": "332 تومان",
        "link": "https://torob.com/p/51267344-c620-4d05-9834-2cbad796a683/%D8%AA%D9%84%D9%88%DB%8C%D8%B2%DB%8C%D9%88%D9%86-%D8%AC%DB%8C-%D9%BE%D9%84%D8%A7%D8%B3-%D9%85%D8%AF%D9%84-gtv-98sq866s-%D8%B3%D8%A7%DB%8C%D8%B2-98-%D8%A7%DB%8C%D9%86%DA%86-qled-ultra-hd-4k/"
    },
    {
        "title": "تلویزیون جی پلاس مدل GTV-98SQ866S سایز ۹۸ اینچ QLED Ultra HD 4K",
        "brand": "جی پلاس",
        "size": "۹۸ اینچ",
        "tech": "QLED",
        "num_sellers": "۲",
        "avg_price_top5": "332 تومان",
        "link": ""
    },
    {
        "title": "تلویزیون هوشمند ایکس ویژن مدل 100X25 سایز ۱۰۰ اینچ QLED Ultra HD 4K",
        "brand": "ایکس ویژن",
        "size": "۱۰۰ اینچ",
        "tech": "QLED",
        "num_sellers": "۷",
        "avg_price_top5": "325 تومان",
        "link": ""
    },
    {
        "title": "تلویزیون سامسونگ 85QN85F",
        "brand": "سامسونگ",
        "size": "نامشخص",
        "tech": "نامشخص",
        "num_sellers": "۶",
        "avg_price_top5": "323 تومان",
        "link": ""
    },
    {
        "title": "تلویزیون سونی XR80 سایز ۶۵ اینچ اولد Ultra HD 4K",
        "brand": "سونی",
        "size": "۶۵ اینچ",
        "tech": "4K",
        "num_sellers": "۱۴",
        "avg_price_top5": "321 تومان",
        "link": ""
    },
    {
        "title": "تلویزیون  ال‌جی مدل 77C3 صفحه نمایش 77 اینچ",
        "brand": "ال‌جی",
        "size": "77 اینچ",
        "tech": "نامشخص",
        "num_sellers": "۲",
        "avg_price_top5": "320 تومان",
        "link": ""
    },
    {
        "title": "تلویزیون سامسونگ مدل 65QN95D سایز ۶۵ اینچ QLED Ultra HD 4K",
        "brand": "سامسونگ",
        "size": "۶۵ اینچ",
        "tech": "QLED",
        "num_sellers": "نامشخص",
        "avg_price_top5": "320 تومان",
        "link": ""
    },
    {
        "title": "تلویزیون هایسنس مدل L9G سایز ۱۰۰ اینچ Ultra HD 4K",
        "brand": "هایسنس",
        "size": "۱۰۰ اینچ",
        "tech": "4K",
        "num_sellers": "نامشخص",
        "avg_price_top5": "317 تومان",
        "link": ""
    },
    {
        "title": "تلویزیون سامسونگ QN85C سایز ۸۵ اینچ کیفیت تصویر Ultra HD 4K QLED",
        "brand": "سامسونگ",
        "size": "۸۵ اینچ",
        "tech": "4K",
        "num_sellers": "نامشخص",
        "avg_price_top5": "315 تومان",
        "link": ""
    },
    {
        "title": "تلویزیون هوشمند هایسنس مدل WR6BE سایز ۶۵ اینچ Ultra HD 4K",
        "brand": "هایسنس",
        "size": "۶۵ اینچ",
        "tech": "4K",
        "num_sellers": "نامشخص",
        "avg_price_top5": "313 تومان",
        "link": ""
    },
    {
        "title": "تلویزیون سونی ۶۵ اینچ براویا ۹ ۲۰۲۴ K-65XR90",
        "brand": "سونی",
        "size": "۶۵ اینچ",
        "tech": "نامشخص",
        "num_sellers": "نامشخص",
        "avg_price_top5": "311 تومان",
        "link": ""
    },
    {
        "title": "تلویزیون هوشمند سام الکترونیک مدل Q80D سایز ۱۰۰ اینچ QLED Ultra HD 4K",
        "brand": "نامشخص",
        "size": "۱۰۰ اینچ",
        "tech": "QLED",
        "num_sellers": "نامشخص",
        "avg_price_top5": "310 تومان",
        "link": ""
    },
    {
        "title": "تلویزیون سامسونگ DU9000 سایز ۹۸ اینچ Ultra HD 4K LED",
        "brand": "سامسونگ",
        "size": "۹۸ اینچ",
        "tech": "4K",
        "num_sellers": "۸",
        "avg_price_top5": "308 تومان",
        "link": ""
    },
    {
        "title": "تلویزیون اسمارت بویمن مدل 86T60 سایز ۸۶ اینچ",
        "brand": "نامشخص",
        "size": "۸۶ اینچ",
        "tech": "نامشخص",
        "num_sellers": "نامشخص",
        "avg_price_top5": "305 تومان",
        "link": ""
    },
    {
        "title": "تلویزیون ال جی G5 سایز ۶۵ اینچ OLED Ultra HD 4K",
        "brand": "ال جی",
        "size": "۶۵ اینچ",
        "tech": "OLED",
        "num_sellers": "۷",
        "avg_price_top5": "302 تومان",
        "link": ""
    },
    {
        "title": "تلویزیون سونی X85L سایز ۸۵ اینچ Ultra HD 4K LED",
        "brand": "سونی",
        "size": "۸۵ اینچ",
        "tech": "4K",
        "num_sellers": "نامشخص",
        "avg_price_top5": "299 تومان",
        "link": ""
    },
    {
        "title": "تلویزیون هایسنس U7K سایز ۱۰۰ اینچ QLED Ultra HD 4K",
        "brand": "هایسنس",
        "size": "۱۰۰ اینچ",
        "tech": "QLED",
        "num_sellers": "۸",
        "avg_price_top5": "295 تومان",
        "link": ""
    },
    {
        "title": "تلویزیون سونی مدل XR50 سایز ۷۵ اینچ LED Ultra HD 4K",
        "brand": "سونی",
        "size": "۷۵ اینچ",
        "tech": "LED",
        "num_sellers": "۱۴",
        "avg_price_top5": "295 تومان",
        "link": ""
    },
    {
        "title": "تلویزیون ال جی ۹۸ اینچ سایز ۹۸ اینچ Ultra HD 4K LED",
        "brand": "ال جی",
        "size": "۹۸ اینچ",
        "tech": "4K",
        "num_sellers": "۸",
        "avg_price_top5": "295 تومان",
        "link": ""
    },
    {
        "title": "تلویزیون شیائومی مدل MAX 2025",
        "brand": "نامشخص",
        "size": "نامشخص",
        "tech": "نامشخص",
        "num_sellers": "نامشخص",
        "avg_price_top5": "294 تومان",
        "link": ""
    },
    {
        "title": "تلویزیون تی سی ال مدل C755 سایز ۷۵ اینچ Ultra HD 4K LED",
        "brand": "تی سی ال",
        "size": "۷۵ اینچ",
        "tech": "4K",
        "num_sellers": "نامشخص",
        "avg_price_top5": "293 تومان",
        "link": ""
    },
    {
        "title": "تلویزیون هوشمند ۵۰ اینچ Crystal UHD سری TU-8000 سامسونگ – 4K HDR، مجهز به الکسا (مدل UN50TU8000FXZA، سال ۲۰۲۰)",
        "brand": "سامسونگ",
        "size": "۵۰ اینچ",
        "tech": "UHD",
        "num_sellers": "نامشخص",
        "avg_price_top5": "288 تومان",
        "link": ""
    },
    {
        "title": "تلویزیون سامسونگ QN85D سایز ۸۵ اینچ Ultra HD 4K QLED",
        "brand": "سامسونگ",
        "size": "۸۵ اینچ",
        "tech": "4K",
        "num_sellers": "۳",
        "avg_price_top5": "288 تومان",
        "link": ""
    },
    {
        "title": "تلویزیون هوشمند جی پلاس مدل GTV-98SQ878SP سایز ۹۸ اینچ QLED Ultra HD 4K",
        "brand": "جی پلاس",
        "size": "۹۸ اینچ",
        "tech": "QLED",
        "num_sellers": "۱۱",
        "avg_price_top5": "285 تومان",
        "link": ""
    },
    {
        "title": "تلویزیون شیائومی MAX 100 سایز ۱۰۰ اینچ QLED کیفیت Ultra HD 4K",
        "brand": "نامشخص",
        "size": "۱۰۰ اینچ",
        "tech": "QLED",
        "num_sellers": "۱۱",
        "avg_price_top5": "284 تومان",
        "link": ""
    },
    {
        "title": "تلویزیون تی سی ال C755 سایز ۸۵ اینچ کیفیت Ultra HD 4K LED",
        "brand": "تی سی ال",
        "size": "۸۵ اینچ",
        "tech": "4K",
        "num_sellers": "۱۶",
        "avg_price_top5": "281 تومان",
        "link": ""
    },
    {
        "title": "تلویزیون هوشمند شیائومی مدل S سایز ۸۵ اینچ LED",
        "brand": "نامشخص",
        "size": "۸۵ اینچ",
        "tech": "LED",
        "num_sellers": "نامشخص",
        "avg_price_top5": "280 تومان",
        "link": ""
    },
    {
        "title": "تلویزیون سامسونگ 85QN70F",
        "brand": "سامسونگ",
        "size": "نامشخص",
        "tech": "نامشخص",
        "num_sellers": "۴",
        "avg_price_top5": "272 تومان",
        "link": ""
    },
    {
        "title": "تلویزیون 98 اینچ جی پلاس مدل 98SQ878SP",
        "brand": "جی پلاس",
        "size": "98 اینچ",
        "tech": "نامشخص",
        "num_sellers": "نامشخص",
        "avg_price_top5": "272 تومان",
        "link": ""
    },
    {
        "title": "تلویزیون توشیبا مدل Z670MW سایز ۸۵ اینچ Ultra HD 4K",
        "brand": "نامشخص",
        "size": "۸۵ اینچ",
        "tech": "4K",
        "num_sellers": "نامشخص",
        "avg_price_top5": "268 تومان",
        "link": ""
    },
    {
        "title": "تلویزیون هوشمند جنرال برلین مدل 98QNED80 سایز ۹۸ اینچ QLED Ultra HD 4K",
        "brand": "نامشخص",
        "size": "۹۸ اینچ",
        "tech": "QLED",
        "num_sellers": "نامشخص",
        "avg_price_top5": "267 تومان",
        "link": ""
    }
]